polars_cloud-0.4.3.dist-info/METADATA
polars_cloud-0.4.3.dist-info/WHEEL
polars_cloud-0.4.3.dist-info/entry_points.txt
polars_cloud-0.4.3.dist-info/licenses/LICENSE
polars_cloud/auth.py
polars_cloud/cli/commands/compute.py
polars_cloud/cli/commands/organization.py
polars_cloud/cli/commands/setup.py
polars_cloud/cli/commands/workspace.py
polars_cloud/cli/commands/_utils.py
polars_cloud/cli/commands/__init__.py
polars_cloud/cli/main.py
polars_cloud/cli/parsers/authenticate.py
polars_cloud/cli/parsers/compute.py
polars_cloud/cli/parsers/login.py
polars_cloud/cli/parsers/main.py
polars_cloud/cli/parsers/organization.py
polars_cloud/cli/parsers/setup.py
polars_cloud/cli/parsers/workspace.py
polars_cloud/cli/parsers/__init__.py
polars_cloud/cli/__init__.py
polars_cloud/config.py
polars_cloud/constants.py
polars_cloud/context/cache.py
polars_cloud/context/compute.py
polars_cloud/context/compute_connect_select.py
polars_cloud/context/compute_specs.py
polars_cloud/context/compute_status.py
polars_cloud/context/__init__.py
polars_cloud/exceptions.py
polars_cloud/organization/organization.py
polars_cloud/organization/__init__.py
polars_cloud/polars_cloud.pyi
polars_cloud/py.typed
polars_cloud/query/dst.py
polars_cloud/query/ext.py
polars_cloud/query/query.py
polars_cloud/query/query_info.py
polars_cloud/query/query_profile.py
polars_cloud/query/query_result.py
polars_cloud/query/query_status.py
polars_cloud/query/_utils.py
polars_cloud/query/__init__.py
polars_cloud/workspace/workspace.py
polars_cloud/workspace/workspace_compute_default.py
polars_cloud/workspace/workspace_status.py
polars_cloud/workspace/__init__.py
polars_cloud/_typing.py
polars_cloud/_utils.py
polars_cloud/_version.py
polars_cloud/__init__.py
polars_cloud/__main__.py
polars_cloud/polars_cloud.pyd
polars_cloud-0.4.3.dist-info/RECORD
