Metadata-Version: 2.4
Name: polars-cloud
Version: 0.4.3
Classifier: Development Status :: 1 - Planning
Classifier: Environment :: Console
Classifier: Intended Audience :: Science/Research
Classifier: License :: OSI Approved :: MIT License
Classifier: Operating System :: OS Independent
Classifier: Programming Language :: Python
Classifier: Programming Language :: Python :: 3
Classifier: Programming Language :: Python :: 3 :: Only
Classifier: Programming Language :: Python :: 3.9
Classifier: Programming Language :: Python :: 3.10
Classifier: Programming Language :: Python :: 3.11
Classifier: Programming Language :: Python :: 3.12
Classifier: Programming Language :: Python :: 3.13
Classifier: Topic :: Scientific/Engineering
Requires-Dist: polars[rt64,cloudpickle]==1.37.1
Requires-Dist: typing-extensions>=4.0 ; python_full_version < '3.13'
License-File: LICENSE
Summary: Execute your Polars workloads in the cloud
Home-Page: https://www.pola.rs/
Author-email: Polars <info@polars.tech>
License: MIT
Requires-Python: >=3.9
Project-URL: Homepage, https://cloud.pola.rs/
